{"v":"5.9.0","fr":29.9700012207031,"ip":0,"op":45.0000018328876,"w":233,"h":233,"nm":"07_KBANK_together_Detail_Emoji_Smile_45f","ddd":0,"assets":[],"layers":[{"ddd":0,"ind":1,"ty":4,"nm":"하트 Shapes","parent":4,"sr":1,"ks":{"o":{"a":0,"k":100,"ix":11},"r":{"a":0,"k":0,"ix":10},"p":{"a":1,"k":[{"i":{"x":0.34,"y":1},"o":{"x":0.14,"y":1},"t":0,"s":[165.99,109.861,0],"to":[0,0,0],"ti":[0,0,0]},{"i":{"x":0.999,"y":1},"o":{"x":0.66,"y":0},"t":10,"s":[165.99,82.861,0],"to":[0,0,0],"ti":[0,0,0]},{"i":{"x":0.5,"y":1},"o":{"x":0.001,"y":0},"t":11.6,"s":[165.99,109.861,0],"to":[0,0,0],"ti":[0,0,0]},{"i":{"x":0.5,"y":1},"o":{"x":0.5,"y":0},"t":13.411,"s":[165.99,117.038,0],"to":[0,0,0],"ti":[0,0,0]},{"i":{"x":0.5,"y":1},"o":{"x":0.5,"y":0},"t":17.035,"s":[165.99,106.692,0],"to":[0,0,0],"ti":[0,0,0]},{"i":{"x":0.5,"y":1},"o":{"x":0.5,"y":0},"t":20.658,"s":[165.99,110.805,0],"to":[0,0,0],"ti":[0,0,0]},{"i":{"x":0.5,"y":1},"o":{"x":0.5,"y":0},"t":24.281,"s":[165.99,109.579,0],"to":[0,0,0],"ti":[0,0,0]},{"i":{"x":0.5,"y":1},"o":{"x":0.5,"y":0},"t":27.904,"s":[165.99,109.944,0],"to":[0,0,0],"ti":[0,0,0]},{"i":{"x":0.5,"y":1},"o":{"x":0.5,"y":0},"t":31.528,"s":[165.99,109.835,0],"to":[0,0,0],"ti":[0,0,0]},{"i":{"x":0.5,"y":1},"o":{"x":0.5,"y":0},"t":35.151,"s":[165.99,109.868,0],"to":[0,0,0],"ti":[0,0,0]},{"i":{"x":0.5,"y":1},"o":{"x":0.5,"y":0},"t":38.774,"s":[165.99,109.858,0],"to":[0,0,0],"ti":[0,0,0]},{"i":{"x":0.34,"y":1},"o":{"x":0.533,"y":0},"t":42.398,"s":[165.99,109.861,0],"to":[0,0,0],"ti":[0,0,0]},{"t":45.0000018328876,"s":[165.99,109.861,0]}],"ix":2,"l":2},"a":{"a":0,"k":[165.99,109.861,0],"ix":1,"l":2},"s":{"a":0,"k":[100,100,100],"ix":6,"l":2}},"ao":0,"shapes":[{"ind":0,"ty":"sh","ix":1,"ks":{"a":0,"k":{"i":[[23.217,-19.511],[-10.882,-27.099],[-4.299,-1.193],[-10.858,8.317]],"o":[[-10.077,-28.752],[5.121,12.753],[4.299,1.193],[23.072,-17.673]],"v":[[168.757,93.526],[132.797,109.59],[155.888,140.789],[191.53,125.893]],"c":true},"ix":2},"nm":"Mask 1","mn":"ADBE Vector Shape - Group","hd":false},{"ty":"fl","c":{"a":0,"k":[1,0.172546386719,0.490203857422,1],"ix":4},"o":{"a":0,"k":100,"ix":5},"r":1,"bm":0,"nm":"Fill 1","mn":"ADBE Vector Graphic - Fill","hd":false}],"ip":0,"op":45.0000018328876,"st":0,"bm":0},{"ddd":0,"ind":2,"ty":4,"nm":"하트 Shapes","parent":4,"sr":1,"ks":{"o":{"a":0,"k":100,"ix":11},"r":{"a":0,"k":0,"ix":10},"p":{"a":1,"k":[{"i":{"x":0.34,"y":1},"o":{"x":0.14,"y":1},"t":0,"s":[82.689,109.925,0],"to":[0,0,0],"ti":[0,0,0]},{"i":{"x":0.999,"y":1},"o":{"x":0.66,"y":0},"t":10,"s":[82.689,82.925,0],"to":[0,0,0],"ti":[0,0,0]},{"i":{"x":0.5,"y":1},"o":{"x":0.001,"y":0},"t":11.6,"s":[82.689,109.925,0],"to":[0,0,0],"ti":[0,0,0]},{"i":{"x":0.5,"y":1},"o":{"x":0.5,"y":0},"t":13.411,"s":[82.689,117.103,0],"to":[0,0,0],"ti":[0,0,0]},{"i":{"x":0.5,"y":1},"o":{"x":0.5,"y":0},"t":17.035,"s":[82.689,106.756,0],"to":[0,0,0],"ti":[0,0,0]},{"i":{"x":0.5,"y":1},"o":{"x":0.5,"y":0},"t":20.658,"s":[82.689,110.869,0],"to":[0,0,0],"ti":[0,0,0]},{"i":{"x":0.5,"y":1},"o":{"x":0.5,"y":0},"t":24.281,"s":[82.689,109.643,0],"to":[0,0,0],"ti":[0,0,0]},{"i":{"x":0.5,"y":1},"o":{"x":0.5,"y":0},"t":27.904,"s":[82.689,110.009,0],"to":[0,0,0],"ti":[0,0,0]},{"i":{"x":0.5,"y":1},"o":{"x":0.5,"y":0},"t":31.528,"s":[82.689,109.9,0],"to":[0,0,0],"ti":[0,0,0]},{"i":{"x":0.5,"y":1},"o":{"x":0.5,"y":0},"t":35.151,"s":[82.689,109.932,0],"to":[0,0,0],"ti":[0,0,0]},{"i":{"x":0.5,"y":1},"o":{"x":0.5,"y":0},"t":38.774,"s":[82.689,109.923,0],"to":[0,0,0],"ti":[0,0,0]},{"i":{"x":0.34,"y":1},"o":{"x":0.533,"y":0},"t":42.398,"s":[82.689,109.925,0],"to":[0,0,0],"ti":[0,0,0]},{"t":45.0000018328876,"s":[82.689,109.925,0]}],"ix":2,"l":2},"a":{"a":0,"k":[82.689,109.925,0],"ix":1,"l":2},"s":{"a":0,"k":[100,100,100],"ix":6,"l":2}},"ao":0,"shapes":[{"ind":0,"ty":"sh","ix":1,"ks":{"a":0,"k":{"i":[[-23.409,-19.348],[10.972,-26.873],[4.334,-1.183],[10.948,8.248]],"o":[[10.16,-28.513],[-5.164,12.646],[-4.334,1.183],[-23.263,-17.527]],"v":[[79.9,93.726],[116.157,109.657],[92.874,140.596],[56.938,125.824]],"c":true},"ix":2},"nm":"Mask 1","mn":"ADBE Vector Shape - Group","hd":false},{"ty":"fl","c":{"a":0,"k":[1,0.172546386719,0.490203857422,1],"ix":4},"o":{"a":0,"k":100,"ix":5},"r":1,"bm":0,"nm":"Fill 1","mn":"ADBE Vector Graphic - Fill","hd":false}],"ip":0,"op":45.0000018328876,"st":0,"bm":0},{"ddd":0,"ind":3,"ty":4,"nm":"입 Shapes","parent":4,"sr":1,"ks":{"o":{"a":0,"k":100,"ix":11},"r":{"a":0,"k":0,"ix":10},"p":{"a":1,"k":[{"i":{"x":0.34,"y":1},"o":{"x":0.14,"y":1},"t":0,"s":[124.582,168.422,0],"to":[0,0,0],"ti":[0,0,0]},{"i":{"x":0.999,"y":1},"o":{"x":0.66,"y":0},"t":10,"s":[124.582,141.422,0],"to":[0,0,0],"ti":[0,0,0]},{"i":{"x":0.5,"y":1},"o":{"x":0.001,"y":0},"t":11.6,"s":[124.582,168.422,0],"to":[0,0,0],"ti":[0,0,0]},{"i":{"x":0.5,"y":1},"o":{"x":0.5,"y":0},"t":13.411,"s":[124.582,175.6,0],"to":[0,0,0],"ti":[0,0,0]},{"i":{"x":0.5,"y":1},"o":{"x":0.5,"y":0},"t":17.035,"s":[124.582,165.254,0],"to":[0,0,0],"ti":[0,0,0]},{"i":{"x":0.5,"y":1},"o":{"x":0.5,"y":0},"t":20.658,"s":[124.582,169.367,0],"to":[0,0,0],"ti":[0,0,0]},{"i":{"x":0.5,"y":1},"o":{"x":0.5,"y":0},"t":24.281,"s":[124.582,168.141,0],"to":[0,0,0],"ti":[0,0,0]},{"i":{"x":0.5,"y":1},"o":{"x":0.5,"y":0},"t":27.904,"s":[124.582,168.506,0],"to":[0,0,0],"ti":[0,0,0]},{"i":{"x":0.5,"y":1},"o":{"x":0.5,"y":0},"t":31.528,"s":[124.582,168.397,0],"to":[0,0,0],"ti":[0,0,0]},{"i":{"x":0.5,"y":1},"o":{"x":0.5,"y":0},"t":35.151,"s":[124.582,168.43,0],"to":[0,0,0],"ti":[0,0,0]},{"i":{"x":0.5,"y":1},"o":{"x":0.5,"y":0},"t":38.774,"s":[124.582,168.42,0],"to":[0,0,0],"ti":[0,0,0]},{"i":{"x":0.34,"y":1},"o":{"x":0.533,"y":0},"t":42.398,"s":[124.582,168.423,0],"to":[0,0,0],"ti":[0,0,0]},{"t":45.0000018328876,"s":[124.582,168.422,0]}],"ix":2,"l":2},"a":{"a":0,"k":[124.582,168.422,0],"ix":1,"l":2},"s":{"a":1,"k":[{"i":{"x":[0.999,0.999,0.999],"y":[1,1,1]},"o":{"x":[0.66,0.66,0.66],"y":[0,0,0]},"t":10,"s":[50,50,100]},{"i":{"x":[0.5,0.5,0.5],"y":[1,1,1]},"o":{"x":[0.001,0.001,0.001],"y":[0,0,0]},"t":11.6,"s":[100,100,100]},{"i":{"x":[0.5,0.5,0.5],"y":[1,1,1]},"o":{"x":[0.5,0.5,0.5],"y":[0,0,0]},"t":13.411,"s":[113.292,113.292,100]},{"i":{"x":[0.5,0.5,0.5],"y":[1,1,1]},"o":{"x":[0.5,0.5,0.5],"y":[0,0,0]},"t":17.035,"s":[94.133,94.133,100]},{"i":{"x":[0.5,0.5,0.5],"y":[1,1,1]},"o":{"x":[0.5,0.5,0.5],"y":[0,0,0]},"t":20.658,"s":[101.749,101.749,100]},{"i":{"x":[0.5,0.5,0.5],"y":[1,1,1]},"o":{"x":[0.5,0.5,0.5],"y":[0,0,0]},"t":24.281,"s":[99.478,99.478,100]},{"i":{"x":[0.5,0.5,0.5],"y":[1,1,1]},"o":{"x":[0.5,0.5,0.5],"y":[0,0,0]},"t":27.904,"s":[100.156,100.156,100]},{"i":{"x":[0.5,0.5,0.5],"y":[1,1,1]},"o":{"x":[0.5,0.5,0.5],"y":[0,0,0]},"t":31.528,"s":[99.954,99.954,100]},{"i":{"x":[0.5,0.5,0.5],"y":[1,1,1]},"o":{"x":[0.5,0.5,0.5],"y":[0,0,0]},"t":35.151,"s":[100.014,100.014,100]},{"i":{"x":[0.5,0.5,0.5],"y":[1,1,1]},"o":{"x":[0.5,0.5,0.5],"y":[0,0,0]},"t":38.774,"s":[99.996,99.996,100]},{"i":{"x":[0.833,0.833,0.833],"y":[1,1,1]},"o":{"x":[0.533,0.533,0.533],"y":[0,0,0]},"t":42.398,"s":[100.001,100.001,100]},{"t":45.0000018328876,"s":[100,100,100]}],"ix":6,"l":2}},"ao":0,"shapes":[{"ind":0,"ty":"sh","ix":1,"ks":{"a":0,"k":{"i":[[0.089,0.257],[0.271,0.11],[0.099,0.033],[1.095,-0.393],[5.889,-0.854],[3.829,-0.059],[9.898,1.752],[3.522,0.676],[0.556,-0.358],[0.083,-0.061],[0.084,-0.291],[-0.064,-0.315],[-22.281,1.484],[0.84,7.802]],"o":[[-0.084,-0.29],[-0.083,-0.061],[-0.557,-0.361],[-3.522,0.677],[-9.896,1.748],[-3.824,-0.058],[-5.887,-0.853],[-1.091,-0.391],[-0.099,0.033],[-0.272,0.11],[-0.089,0.257],[-0.841,7.802],[22.282,1.483],[0.064,-0.316]],"v":[[163.918,154.446],[163.365,153.868],[163.093,153.726],[160.581,153.854],[145.249,157.685],[124.579,159.534],[103.91,157.682],[88.577,153.854],[86.073,153.726],[85.801,153.868],[85.246,154.446],[85.212,155.306],[124.582,183.271],[163.953,155.306]],"c":true},"ix":2},"nm":"Mask 1","mn":"ADBE Vector Shape - Group","hd":false},{"ind":1,"ty":"sh","ix":2,"ks":{"a":0,"k":{"i":[[-3.174,0.218],[1.804,-0.033],[2.695,0.162],[-1.606,-0.029]],"o":[[-3.169,0.222],[-1.608,-0.031],[2.696,0.159],[1.805,-0.031]],"v":[[132.057,160.541],[124.582,160.821],[118.118,160.605],[124.579,160.814]],"c":true},"ix":2},"nm":"Mask 2","mn":"ADBE Vector Shape - Group","hd":false},{"ty":"fl","c":{"a":0,"k":[0.521575927734,0.239227294922,0.105895996094,1],"ix":4},"o":{"a":0,"k":100,"ix":5},"r":1,"bm":0,"nm":"Fill 1","mn":"ADBE Vector Graphic - Fill","hd":false}],"ip":0,"op":45.0000018328876,"st":0,"bm":0},{"ddd":0,"ind":4,"ty":4,"nm":"얼굴 Shapes","sr":1,"ks":{"o":{"a":0,"k":100,"ix":11},"r":{"a":0,"k":0,"ix":10},"p":{"a":0,"k":[116.582,116.345,0],"ix":2,"l":2},"a":{"a":0,"k":[124.582,124.345,0],"ix":1,"l":2},"s":{"a":1,"k":[{"i":{"x":[0.999,0.999,0.999],"y":[1,1,1]},"o":{"x":[0.14,0.14,0.14],"y":[0.68,0.68,0]},"t":0,"s":[0,0,100]},{"i":{"x":[0.5,0.5,0.5],"y":[1,1,1]},"o":{"x":[0.001,0.001,0.001],"y":[0,0,0]},"t":3.4,"s":[100,100,100]},{"i":{"x":[0.5,0.5,0.5],"y":[1,1,1]},"o":{"x":[0.5,0.5,0.5],"y":[0,0,0]},"t":5.066,"s":[117.885,117.885,100]},{"i":{"x":[0.5,0.5,0.5],"y":[1,1,1]},"o":{"x":[0.5,0.5,0.5],"y":[0,0,0]},"t":8.4,"s":[94.125,94.125,100]},{"i":{"x":[0.5,0.5,0.5],"y":[1,1,1]},"o":{"x":[0.5,0.5,0.5],"y":[0,0,0]},"t":11.734,"s":[101.93,101.93,100]},{"i":{"x":[0.5,0.5,0.5],"y":[1,1,1]},"o":{"x":[0.5,0.5,0.5],"y":[0,0,0]},"t":15.066,"s":[99.366,99.366,100]},{"i":{"x":[0.5,0.5,0.5],"y":[1,1,1]},"o":{"x":[0.5,0.5,0.5],"y":[0,0,0]},"t":18.4,"s":[100.208,100.208,100]},{"i":{"x":[0.5,0.5,0.5],"y":[1,1,1]},"o":{"x":[0.5,0.5,0.5],"y":[0,0,0]},"t":21.734,"s":[99.932,99.932,100]},{"i":{"x":[0.5,0.5,0.5],"y":[1,1,1]},"o":{"x":[0.5,0.5,0.5],"y":[0,0,0]},"t":25.066,"s":[100.022,100.022,100]},{"i":{"x":[0.833,0.833,0.833],"y":[1,1,1]},"o":{"x":[0.5,0.5,0.5],"y":[0,0,0]},"t":28.4,"s":[99.993,99.993,100]},{"t":30.0000012219251,"s":[100,100,100]}],"ix":6,"l":2}},"ao":0,"shapes":[{"ind":0,"ty":"sh","ix":1,"ks":{"a":0,"k":{"i":[[-53.41,0],[0,-53.41],[53.41,0],[0,53.409]],"o":[[53.41,0],[0,53.409],[-53.41,0],[0,-53.41]],"v":[[124.582,27.638],[221.289,124.346],[124.582,221.052],[27.875,124.346]],"c":true},"ix":2},"nm":"Mask 1","mn":"ADBE Vector Shape - Group","hd":false},{"ty":"fl","c":{"a":0,"k":[1,0.870574951172,0.113739013672,1],"ix":4},"o":{"a":0,"k":100,"ix":5},"r":1,"bm":0,"nm":"Fill 1","mn":"ADBE Vector Graphic - Fill","hd":false},{"ty":"st","c":{"a":0,"k":[1,0.823529422283,0,1],"ix":3},"o":{"a":0,"k":100,"ix":4},"w":{"a":0,"k":4,"ix":5},"lc":1,"lj":1,"ml":4,"bm":0,"nm":"Stroke 1","mn":"ADBE Vector Graphic - Stroke","hd":false}],"ip":0,"op":45.0000018328876,"st":0,"bm":0}],"markers":[]}