{"v":"4.8.0","meta":{"g":"LottieFiles AE ","a":"","k":"","d":"","tc":""},"fr":29.9700012207031,"ip":0,"op":40.0000016292334,"w":184,"h":242,"nm":"02_KBANK_together_Primerate_Arrow","ddd":0,"assets":[],"layers":[{"ddd":0,"ind":1,"ty":3,"nm":"▣ Void 1","sr":1,"ks":{"o":{"a":0,"k":100,"ix":11},"r":{"a":0,"k":0,"ix":10},"p":{"s":true,"x":{"a":0,"k":82.75,"ix":3},"y":{"a":0,"k":166,"ix":4}},"a":{"a":0,"k":[0,0,0],"ix":1},"s":{"a":0,"k":[100,100,100],"ix":6}},"ao":0,"ef":[{"ty":5,"nm":"Void","np":20,"mn":"Pseudo/289611","ix":1,"en":1,"ef":[{"ty":0,"nm":"Width","mn":"Pseudo/289611-0001","ix":1,"v":{"a":0,"k":100,"ix":1}},{"ty":0,"nm":"Height","mn":"Pseudo/289611-0002","ix":2,"v":{"a":0,"k":100,"ix":2}},{"ty":0,"nm":"Offset X","mn":"Pseudo/289611-0003","ix":3,"v":{"a":0,"k":0,"ix":3}},{"ty":0,"nm":"Offset Y","mn":"Pseudo/289611-0004","ix":4,"v":{"a":0,"k":0,"ix":4}},{"ty":6,"nm":"About","mn":"Pseudo/289611-0005","ix":5,"v":0},{"ty":6,"nm":"Plague of null layers.","mn":"Pseudo/289611-0006","ix":6,"v":0},{"ty":6,"nm":"Void","mn":"Pseudo/289611-0007","ix":7,"v":0},{"ty":6,"nm":"Following projects","mn":"Pseudo/289611-0008","ix":8,"v":0},{"ty":6,"nm":"Void","mn":"Pseudo/289611-0009","ix":9,"v":0},{"ty":6,"nm":"through time.","mn":"Pseudo/289611-0010","ix":10,"v":0},{"ty":6,"nm":"Void","mn":"Pseudo/289611-0011","ix":11,"v":0},{"ty":6,"nm":"Be free of the past.","mn":"Pseudo/289611-0012","ix":12,"v":0},{"ty":6,"nm":"Void","mn":"Pseudo/289611-0013","ix":13,"v":0},{"ty":6,"nm":"Void - 1.0.1","mn":"Pseudo/289611-0014","ix":14,"v":0},{"ty":6,"nm":"Void","mn":"Pseudo/289611-0015","ix":15,"v":0},{"ty":6,"nm":"?2022 Battle Axe Inc","mn":"Pseudo/289611-0016","ix":16,"v":0},{"ty":6,"nm":"Void","mn":"Pseudo/289611-0017","ix":17,"v":0},{"ty":6,"nm":"Void","mn":"Pseudo/289611-0018","ix":18,"v":0}]}],"ip":0,"op":40.0000016292334,"st":0,"bm":0},{"ddd":0,"ind":2,"ty":4,"nm":"Shape 27 copy Shapes","parent":1,"sr":1,"ks":{"o":{"a":0,"k":100,"ix":11},"r":{"a":0,"k":0,"ix":10},"p":{"a":0,"k":[-89.25,-64.5,0],"ix":2},"a":{"a":0,"k":[188.5,139.5,0],"ix":1},"s":{"a":0,"k":[100,100,100],"ix":6}},"ao":0,"shapes":[{"ty":"gr","it":[{"ind":0,"ty":"sh","ix":1,"ks":{"a":0,"k":{"i":[[0,0],[-119.831,-334.792]],"o":[[0,0],[119.831,334.792]],"v":[[1,5.998],[375.253,277.998]],"c":true},"ix":2},"nm":"Mask 1","mn":"ADBE Vector Shape - Group","hd":false},{"ty":"st","c":{"a":0,"k":[1,1,1,1],"ix":3},"o":{"a":0,"k":100,"ix":4},"w":{"a":0,"k":2,"ix":5},"lc":2,"lj":2,"bm":0,"nm":"Stroke 1","mn":"ADBE Vector Graphic - Stroke","hd":false},{"ty":"tm","s":{"a":1,"k":[{"i":{"x":[0.1],"y":[1]},"o":{"x":[0.9],"y":[0]},"t":18,"s":[0]},{"t":33.0000013441176,"s":[44]}],"ix":1},"e":{"a":1,"k":[{"i":{"x":[0.1],"y":[1]},"o":{"x":[0.9],"y":[0]},"t":0,"s":[0]},{"t":15.0000006109625,"s":[44]}],"ix":2},"o":{"a":0,"k":0,"ix":3},"m":1,"ix":3,"nm":"Trim Paths 1","mn":"ADBE Vector Filter - Trim","hd":false},{"ty":"tr","p":{"a":0,"k":[0,0],"ix":2},"a":{"a":0,"k":[0,0],"ix":1},"s":{"a":0,"k":[100,100],"ix":3},"r":{"a":0,"k":0,"ix":6},"o":{"a":0,"k":100,"ix":7},"sk":{"a":0,"k":0,"ix":4},"sa":{"a":0,"k":0,"ix":5},"nm":"Transform"}],"nm":"Group 1","np":3,"cix":2,"bm":0,"ix":1,"mn":"ADBE Vector Group","hd":false},{"ty":"gr","it":[{"ind":0,"ty":"sh","ix":1,"ks":{"a":0,"k":{"i":[[0,0],[-9.962,-6.945],[0.406,10.588]],"o":[[0,0],[0,0],[-0.089,-2.318]],"v":[[1.289,10.999],[19.253,19.998],[20.923,1.435]],"c":true},"ix":2},"nm":"Mask 1","mn":"ADBE Vector Shape - Group","hd":false},{"ty":"tm","s":{"a":1,"k":[{"i":{"x":[0.1],"y":[1]},"o":{"x":[0.9],"y":[0]},"t":18,"s":[0]},{"t":33.0000013441176,"s":[64]}],"ix":1},"e":{"a":1,"k":[{"i":{"x":[0.1],"y":[1]},"o":{"x":[0.9],"y":[0]},"t":10,"s":[0]},{"t":15.0000006109625,"s":[64]}],"ix":2},"o":{"a":0,"k":-4,"ix":3},"m":1,"ix":2,"nm":"Trim Paths 1","mn":"ADBE Vector Filter - Trim","hd":false},{"ty":"st","c":{"a":0,"k":[1,1,1,1],"ix":3},"o":{"a":0,"k":100,"ix":4},"w":{"a":0,"k":2,"ix":5},"lc":2,"lj":2,"bm":0,"nm":"Stroke 1","mn":"ADBE Vector Graphic - Stroke","hd":false},{"ty":"tr","p":{"a":0,"k":[356.25,258],"ix":2},"a":{"a":0,"k":[0,0],"ix":1},"s":{"a":0,"k":[100,100],"ix":3},"r":{"a":0,"k":0,"ix":6},"o":{"a":0,"k":100,"ix":7},"sk":{"a":0,"k":0,"ix":4},"sa":{"a":0,"k":0,"ix":5},"nm":"Transform"}],"nm":"Group 2","np":3,"cix":2,"bm":0,"ix":2,"mn":"ADBE Vector Group","hd":false}],"ip":0,"op":40.0000016292334,"st":0,"bm":0}],"markers":[]}